{
  "$schema": "https://static.modelcontextprotocol.io/schemas/2025-12-11/server.schema.json",
  "name": "io.github.mlawsonking/web-tools-mcp",
  "description": "Deterministic web tools for AI agents: read URLs, metadata, email, scrape, RSS, DNS, SSL, HTTP.",
  "repository": {
    "url": "https://github.com/mlawsonking/MCP",
    "source": "github",
    "subfolder": "agent-tools-mcp"
  },
  "version": "1.0.2",
  "packages": [
    {
      "registryType": "npm",
      "identifier": "web-tools-mcp",
      "version": "1.0.2",
      "transport": { "type": "stdio" }
    }
  ]
}
